
<Objectives>
 <Objective id="844024417256731762" title="@loc_15373294129891630348" optional="false">
  <Descriptions>
   <Desc id="844024417284708579" displayName="DSLocked" text="@loc_15373294129891630349"/>
   <Desc id="844024417284709791" displayName="DSLocked_DeadJanuary" text="@loc_15373294129891630350"/>
   <Desc id="935634234982" displayName="Find Voice Samples" text="@loc_15373294129891630351"/>
   <Desc id="844024417269155106" displayName="Find Voice Samples ALT" text="@loc_15373294129891630352"/>
   <Desc id="844024417256731763" displayName="Completed" text="@loc_15373294129891630353"/>
   <Desc id="844024417269155396" displayName="Completed ALT" text="@loc_15373294129891630354"/>
  </Descriptions>
  <Tasks>
   <Task id="844024417289995196" displayName="Find samples 10%" optional="false" text="@loc_15373294129891630366" Location="844024417252490146" targetCharacterId="844024417289995197"/>
   <Task id="844024417269155129" displayName="Find samples 20%" optional="false" text="@loc_15373294129891630355" Location="844024417252490146"/>
   <Task id="844024417289645580" displayName="Find samples 30%" optional="false" text="@loc_15373294129891630356" Location="844024417252490146" targetCharacterId="844024417289645581"/>
   <Task id="844024417269155448" displayName="Find samples 40%" optional="false" text="@loc_15373294129891630357" targetCharacterId="844024417269155449" Location="844024417252490146"/>
   <Task id="844024417289645687" displayName="Find samples 50%" optional="false" text="@loc_15373294129891630358" targetCharacterId="844024417289645688" Location="844024417252490146"/>
   <Task id="844024417269155450" displayName="Find samples 60%" optional="false" text="@loc_15373294129891630359" targetCharacterId="844024417269155451" Location="844024417252490146"/>
   <Task id="844024417289645698" displayName="Find samples 70%" optional="false" text="@loc_15373294129891630360" targetCharacterId="844024417289645699" Location="844024417252490146"/>
   <Task id="844024417269155452" displayName="Find samples 80%" optional="false" text="@loc_15373294129891630361" targetCharacterId="844024417269155453" Location="844024417252490146"/>
   <Task id="844024417289645644" displayName="Find samples 90%" optional="false" text="@loc_15373294129891630362" Location="844024417252490146" targetCharacterId="844024417289645645"/>
   <Task id="12889009725037460810" displayName="Find samples 100%" optional="false" text="@loc_15373294129891630363" Location="844024417252490146" targetCharacterId="12889009725037460811"/>
   <Task id="844024417269160429" displayName="UnlockDeepStorage" optional="false" text="@loc_15373294129891630364" Location="1713490239386284818"/>
   <Task id="844024417280407079" displayName="Find samples 0%" optional="false" text="@loc_15373294129891630365" Location="844024417252490146"/>
   <Task id="844024417284708846" displayName="InvestigateForClues" optional="true" text="@loc_15373294129891630367" Location="1713490239386284818"/>
   <Task id="844024417282905496" displayName="Sample_DaniellesRoom" optional="true" text="@loc_15373294129891630369" markerLabel="@loc_15373294129891630368" Location="844024417252490146"/>
   <Task id="844024417302781507" displayName="Sample_SkysPod" optional="false" text="@loc_15373294129891630371" markerLabel="@loc_15373294129891630370" Location="844024417252490146" targetCharacterId="844024417302781508"/>
   <Task id="844024417300528515" displayName="Sample_Theater" optional="false" text="@loc_15373294129891630373" markerLabel="@loc_15373294129891630372" Location="844024417252490146"/>
   <Task id="844024417300956979" displayName="Sample_Band" optional="true" text="@loc_15373294129891630375" markerLabel="@loc_15373294129891630374" targetCharacterId="844024417300956980" Location="844024417252490146"/>
   <Task id="844024417300528523" displayName="Sample_AbbyRoom" optional="false" text="@loc_15373294129891630377" Location="844024417252490146" markerLabel="@loc_15373294129891630376"/>
   <Task id="844024417300528534" displayName="Sample_GamingTable" optional="false" text="@loc_15373294129891630379" markerLabel="@loc_15373294129891630378" Location="844024417252490146"/>
   <Task id="844024417300528497" displayName="Sample_Emma_A" optional="false" text="@loc_15373294129891630381" markerLabel="@loc_15373294129891630380" Location="844024417252490146"/>
   <Task id="12889009725044276714" displayName="RecordSong" optional="false" text="@loc_12889009725044276715" timerLabel="@loc_13680621263407628210"/>
  </Tasks>
  <Clues>
   <Clue id="844024417273227082" displayName="CharacterSheet" text="@loc_15373294129891630382"/>
   <Clue id="844024417273227121" displayName="LostTranscribe" text="@loc_15373294129891630383"/>
   <Clue id="844024417273227122" displayName="BrokenTranscribe" text="@loc_15373294129891630384"/>
   <Clue id="844024417273227124" displayName="Band" text="@loc_15373294129891630385"/>
   <Clue id="844024417273227194" displayName="[DEPRECATED]Cook" text="@loc_15373294129891630386"/>
   <Clue id="844024417273227221" displayName="AbbysRoom" text="@loc_15373294129891630387"/>
   <Clue id="844024417273227247" displayName="Abby" text="@loc_15373294129891630388"/>
   <Clue id="844024417294574096" displayName="PasswordLocation" text="@loc_15373294129891630389"/>
   <Clue id="844024417294844755" displayName="AbbysKey" text="@loc_15373294129891630390"/>
   <Clue id="844024417298535243" displayName="Skye&apos;s Bunk" text="@loc_15373294129891630391"/>
   <Clue id="12889009725041669695" displayName="TraumaClue" text="@loc_15373294129891630392"/>
   <Clue id="12889009725035730169" displayName="EmmaClue" text="@loc_15373294129891630393"/>
  </Clues>
 </Objective>
</Objectives>