
<ArkAiTree>
 <Root>
  <ArkAiTreeStackNode>
   <Children>
    <ArkAiTreeFleeNode corneredBehavior="0" bCanShift="false" bFleesFromHostileEntity="false" chanceToCowerAfterMove="0.0" endFearDelayTime="5.0" overrideFleeSpeedLiteral="0.0" resumeFleeAfterCowerRadius="5.0" retryBreakCowerAfterFailedFleeTime="5.0">
     <FleeSearchRadius minimum="10" maximum="25"/>
    </ArkAiTreeFleeNode>
    <ArkAiTreeHypnotizedNode/>
    <ArkAiTreeScriptMoveNode/>
    <ArkAiTreeCreatePhantomNode bPromptFromCombat="true" maxTimeToAttemptRaise="3.0" defaultCreatePhantomAbilityContextId="100250" defaultNoMovementContextId="100254" initialReachableCheckSearchRadius="3.0">
     <PossiblePhantomArchetypeNames>
      <Element value="ArkNpcs.Phantoms.BasePhantom"/>
      <Element value="ArkNpcs.Phantoms.EthericPhantom"/>
      <Element value="ArkNpcs.Phantoms.ThermalPhantom"/>
      <Element value="ArkNpcs.Phantoms.VoltaicPhantom"/>
     </PossiblePhantomArchetypeNames>
     <CorrespondingRaisePhantomContextIds>
      <Element value="100250"/>
      <Element value="100251"/>
      <Element value="100252"/>
      <Element value="100253"/>
     </CorrespondingRaisePhantomContextIds>
     <NoMovementRaisePhantomContextIds>
      <Element value="100254"/>
      <Element value="100255"/>
      <Element value="100256"/>
      <Element value="100257"/>
     </NoMovementRaisePhantomContextIds>
    </ArkAiTreeCreatePhantomNode>
    <ArkAiTreeCombatSearchForHiddenMimicPlayer searchFailsafeTime="10.0" bAllowShifting="false" timeUntilShiftEnabled="0.0" combatSearchSpeed="0" movementStopDistance="2.0" throttleCanSeeTimer="0.5">
     <ValidPointSearchBounds horizontalDistance="10.0" downDistance="5.0" upDistance="5.0"/>
    </ArkAiTreeCombatSearchForHiddenMimicPlayer>
    <ArkAiTreeWeaverEscapeNode nearbyThreatDistance="5.0" farawayAndSeenThreatDistance="20.0" nearbyAndSeenThreatDistance="10.0">
     <FsmConfig maxTimeToTryLaunchCystoids="10.0" callForHelpGameNoiseTypeId="10850392949532183295" callForHelpGameNoiseLoudness="10850392949532183297" alarmCallAudioTrigger="Play_Weaver_Alarm_Call" launchCystoidsContextId="100200" callForHelpCooldown="3.0" maxRetreatAttempts="3" bStartInDebugState="false" moveToCorpseStopDistance="2.0" retreatPointSearchMinDistanceFromWeaver="5.0" attackAttemptTimeBeforeFleeing="2.5">
      <CorpseSearchBounds horizontalDistance="50.0" downDistance="50.0" upDistance="50.0"/>
      <CorpseNavPointSearchBounds horizontalDistance="20.0" downDistance="20.0" upDistance="20.0"/>
      <AvoidEnemyRetreatCheckBounds horizontalDistance="5.0" downDistance="5.0" upDistance="5.0"/>
      <RetreatPointSearchBounds horizontalDistance="75.0" downDistance="75.0" upDistance="75.0"/>
     </FsmConfig>
    </ArkAiTreeWeaverEscapeNode>
    <ArkAiTreeNoticeNode speed="fastest">
     <InterruptNoticeAnimDistance minimum="0.0" maximum="4.0"/>
     <InterruptNoticeAnimMinPlayTime minimum="0.0" maximum="0.5"/>
    </ArkAiTreeNoticeNode>
    <ArkAiTreeCreatePhantomNode bPromptFromCombat="false" maxTimeToAttemptRaise="3.0" defaultCreatePhantomAbilityContextId="100250" defaultNoMovementContextId="100254" initialReachableCheckSearchRadius="3.0">
     <PossiblePhantomArchetypeNames>
      <Element value="ArkNpcs.Phantoms.BasePhantom"/>
      <Element value="ArkNpcs.Phantoms.EthericPhantom"/>
      <Element value="ArkNpcs.Phantoms.ThermalPhantom"/>
      <Element value="ArkNpcs.Phantoms.VoltaicPhantom"/>
     </PossiblePhantomArchetypeNames>
     <CorrespondingRaisePhantomContextIds>
      <Element value="100250"/>
      <Element value="100251"/>
      <Element value="100252"/>
      <Element value="100253"/>
     </CorrespondingRaisePhantomContextIds>
     <NoMovementRaisePhantomContextIds>
      <Element value="100254"/>
      <Element value="100255"/>
      <Element value="100256"/>
      <Element value="100257"/>
     </NoMovementRaisePhantomContextIds>
    </ArkAiTreeCreatePhantomNode>
    <ArkAiTreeDistractedNode>
     <config distractionCloseArrivalDistance="1.75" distractionCloseFailTimerDuration="10.0" distractionStopArrivalDistance="0.1" distractionMoveDistanceFail="4.0"/>
    </ArkAiTreeDistractedNode>
    <ArkAiTreePatrolNode patrolDialogPulseTime="1.0" timeToGiveupUnreachablePatrol="20.0" patrolIdleCooldown="2.0"/>
    <ArkAiTreeGuardNode/>
    <ArkAiTreeWanderNode maxDistanceToWander="10" minDistanceToNextWanderPoint="5.0" chanceToRandomWander="0.33000001" bStartsActive="true" attractorRadius="50" randomWaitIdleAnimChance="0" tryFollowLeaderDist="5.0">
     <RandomWaitPeriod minimum="8" maximum="17"/>
     <NumPointsToWanderInAreasBeforeChange minimum="4" maximum="9"/>
    </ArkAiTreeWanderNode>
   </Children>
  </ArkAiTreeStackNode>
 </Root>
</ArkAiTree>