
<Graph Description="" Group="" enabled="1" MultiPlayer="ClientServer">
 <Nodes>
  <Node Id="2" Class="Ark:Objectives:TaskState" pos="90,-220,0">
   <Inputs task_Task="-6622188701083418291" ShowOnHUD="1" Timer="0" ShowTimerOnHUD="0"/>
  </Node>
  <Node Id="3" Class="Ark:Objectives:TaskState" pos="-530,1910,0">
   <Inputs task_Task="844024417276162358" ShowOnHUD="0" Timer="0" ShowTimerOnHUD="0"/>
  </Node>
  <Node Id="7" Class="Logic:Gate" pos="-100,1890,0">
   <Inputs SetClosed="0" AutoCloseCount="1" Reset="0"/>
  </Node>
  <Node Id="9" Class="Mission:GameTokenUpdated" pos="-530,1800,0">
   <Inputs gametokenid_Token="80397968" compare_Value="true"/>
  </Node>
  <Node Id="15" Class="Ark:Objectives:ObjectiveState" pos="-610,470,0">
   <Inputs objective_Objective="844024417256800376" SetTracked="1" ShowOnHUD="1"/>
  </Node>
  <Node Id="17" Class="Ark:Objectives:SetObjectiveDescription" pos="-160,400,0">
   <Inputs objectiveDescription_Description="844024417256800377"/>
  </Node>
  <Node Id="18" Class="Ark:Objectives:ObjectiveState" pos="-160,550,0">
   <Inputs objective_Objective="844024417275569839" SetTracked="1" ShowOnHUD="1"/>
  </Node>
  <Node Id="19" Class="Ark:Objectives:SetObjectiveDescription" pos="450,470,0">
   <Inputs objectiveDescription_Description="844024417275569840"/>
  </Node>
  <Node Id="21" Class="Ark:Objectives:TaskState" pos="240,570,0">
   <Inputs task_Task="6732635291233575427" ShowOnHUD="1" Timer="0" ShowTimerOnHUD="0"/>
  </Node>
  <Node Id="207" Class="Ark:Objectives:TaskState" pos="90,-800,0">
   <Inputs task_Task="-6622188701083418291" ShowOnHUD="1" Timer="0" ShowTimerOnHUD="0"/>
  </Node>
  <Node Id="635" Class="Ark:Objectives:TaskState" pos="90,-990,0">
   <Inputs task_Task="1713490239370915176" ShowOnHUD="1" Timer="0" ShowTimerOnHUD="0"/>
  </Node>
  <Node Id="636" Class="Ark:Objectives:SetObjectiveDescription" pos="100,-610,0">
   <Inputs objectiveDescription_Description="4349723564879890144"/>
  </Node>
  <Node Id="672" Class="Ark:Objectives:ObjectiveState" pos="-550,-810,0">
   <Inputs objective_Objective="844024417256800376" SetTracked="1" ShowOnHUD="1"/>
  </Node>
  <Node Id="674" Name="Keys_to_the_kingdom,_start" Class="_commentbox" pos="-600,-1008,0">
   <Inputs TextSize="1" Color="0.27451,0.352941,0.705882" DisplayFilled="1" DisplayBox="1" SortPriority="16"/>
   <CommentBox Width="1240" Height="490"/>
  </Node>
  <Node Id="675" Name="Message_from_Alex" Class="_commentbox" pos="-630,-1548,0">
   <Inputs TextSize="1" Color="0.27451,0.352941,0.705882" DisplayFilled="1" DisplayBox="1" SortPriority="16"/>
   <CommentBox Width="1590" Height="390"/>
  </Node>
  <Node Id="679" Class="Ark:Dialog:ConversationEvent" pos="-580,-1400,0">
   <Inputs conversation_Conversation="13680621263364681832"/>
  </Node>
  <Node Id="681" Class="Ark:Objectives:TaskState" pos="390,-1500,0">
   <Inputs task_Task="844024417284033794" ShowOnHUD="1" Timer="0" ShowTimerOnHUD="0"/>
  </Node>
  <Node Id="685" Class="Ark:Objectives:GetTaskState" pos="-450,-220,0">
   <Inputs task_Task="-6622188701083418291"/>
  </Node>
  <Node Id="687" Class="Mission:GameTokenSet" pos="-410,-340,0">
   <Inputs gametokenid_Token="1935128117" Value="true"/>
  </Node>
  <Node Id="688" Class="Mission:GameTokenSet" pos="-1030,1070,0">
   <Inputs gametokenid_Token="80397968" Value="true"/>
  </Node>
  <Node Id="693" Class="Logic:Gate" pos="-780,-300,0">
   <Inputs SetClosed="0" AutoCloseCount="1" Reset="0"/>
  </Node>
  <Node Id="694" Name="Player_gets_Morgan&apos;s_key" Class="_commentbox" pos="-1050,-423,0">
   <Inputs TextSize="1" Color="0.27451,0.352941,0.705882" DisplayFilled="1" DisplayBox="1" SortPriority="16"/>
   <CommentBox Width="2060" Height="530"/>
  </Node>
  <Node Id="695" Name="TODO:_figure_out_what_tasks_to_close_out_here" Class="_comment" pos="-610,650,0"/>
  <Node Id="696" Name="Transitioning_to_Perdition" Class="_commentbox" pos="-2200,315,0">
   <Inputs TextSize="1" Color="0.27451,0.352941,0.705882" DisplayFilled="1" DisplayBox="1" SortPriority="16"/>
   <CommentBox Width="2990" Height="440"/>
  </Node>
  <Node Id="704" Class="Ark:Objectives:GetTaskState" pos="1070,-20,0">
   <Inputs task_Task="844024417275827455"/>
  </Node>
  <Node Id="705" Class="Ark:Objectives:GetTaskState" pos="1070,-310,0">
   <Inputs task_Task="844024417284033794"/>
  </Node>
  <Node Id="706" Class="Ark:Objectives:GetTaskState" pos="1070,-160,0">
   <Inputs task_Task="844024417286532599"/>
  </Node>
  <Node Id="708" Name="Update_the_objective_description_to_no_longer_mention_Morgan&apos;s_key" Class="_commentbox" pos="1040,-333,0">
   <Inputs TextSize="1" Color="0.27451,0.352941,0.705882" DisplayFilled="1" DisplayBox="1" SortPriority="16"/>
   <CommentBox Width="1026" Height="430"/>
  </Node>
  <Node Id="721" Name="Player_gets_Alex&apos;s_key" Class="_commentbox" pos="-1560,1002,0">
   <Inputs TextSize="1" Color="0.27451,0.352941,0.705882" DisplayFilled="1" DisplayBox="1" SortPriority="16"/>
   <CommentBox Width="1400" Height="210"/>
  </Node>
  <Node Id="723" Class="Mission:GameTokenUpdated" pos="70,2440,0">
   <Inputs gametokenid_Token="1935128117" compare_Value="true"/>
  </Node>
  <Node Id="724" Class="Mission:GameTokenUpdated" pos="520,1510,0">
   <Inputs gametokenid_Token="80397968" compare_Value="true"/>
  </Node>
  <Node Id="729" Class="Logic:Gate" pos="40,-1430,0">
   <Inputs SetClosed="0" AutoCloseCount="1" Reset="0"/>
  </Node>
  <Node Id="731" Class="Ark:Debug:ConsoleEvent" pos="-2750,600,0">
   <Inputs Command="startKeyListeners"/>
  </Node>
  <Node Id="733" Class="Inventory:ItemCheck" pos="-550,100,0">
   <Inputs entityId="0" Active="0" archetype="ArkPickups.MissionItems.SelfDestructKey_Alex" itemClass=""/>
  </Node>
  <Node Id="734" Class="Inventory:ItemCheck" pos="-540,800,0">
   <Inputs entityId="0" Active="0" archetype="ArkPickups.MissionItems.SelfDestructKey_Morgan" itemClass=""/>
  </Node>
  <Node Id="736" Class="Logic:Gate" pos="-880,480,0">
   <Inputs SetClosed="0" AutoCloseCount="1" Reset="0"/>
  </Node>
  <Node Id="738" Class="Debug:DisplayMessage" pos="-1000,760,0">
   <Inputs entityId="0" message="got alex key, have morgan key?" DisplayTime="3" posX="50" posY="50" fontSize="2" clr_Color="1,1,1" centered="0" ShowInLauncher="1"/>
  </Node>
  <Node Id="739" Class="Debug:DisplayMessage" pos="200,230,0">
   <Inputs entityId="0" message="yes" DisplayTime="3" posX="50" posY="100" fontSize="2" clr_Color="1,1,1" centered="0" ShowInLauncher="1"/>
  </Node>
  <Node Id="740" Class="Debug:DisplayMessage" pos="200,10,0">
   <Inputs entityId="0" message="no" DisplayTime="3" posX="50" posY="100" fontSize="2" clr_Color="1,1,1" centered="0" ShowInLauncher="1"/>
  </Node>
  <Node Id="741" Class="Debug:DisplayMessage" pos="-950,110,0">
   <Inputs entityId="0" message="got morgan key, have alex key?" DisplayTime="3" posX="50" posY="50" fontSize="2" clr_Color="1,1,1" centered="0" ShowInLauncher="1"/>
  </Node>
  <Node Id="749" Class="Inventory:ItemListener" pos="-1930,580,0">
   <Inputs entityId="0" archetype="ArkPickups.MissionItems.SelfDestructKey_Alex"/>
  </Node>
  <Node Id="750" Class="Logic:Sequentializer" pos="-1130,490,0">
   <Inputs Closed="0" Reverse="0"/>
  </Node>
  <Node Id="751" Class="Inventory:ItemListener" pos="-1970,370,0">
   <Inputs entityId="0" archetype="ArkPickups.MissionItems.SelfDestructKey_Morgan"/>
  </Node>
  <Node Id="753" Class="Debug:DisplayMessage" pos="30,920,0">
   <Inputs entityId="0" message="yes" DisplayTime="3" posX="50" posY="100" fontSize="2" clr_Color="1,1,1" centered="0" ShowInLauncher="1"/>
  </Node>
  <Node Id="754" Class="Debug:DisplayMessage" pos="30,700,0">
   <Inputs entityId="0" message="no" DisplayTime="3" posX="50" posY="100" fontSize="2" clr_Color="1,1,1" centered="0" ShowInLauncher="1"/>
  </Node>
  <Node Id="755" Class="Logic:Gate" pos="-1430,390,0">
   <Inputs SetClosed="0" AutoCloseCount="1" Reset="0"/>
  </Node>
  <Node Id="756" Class="Logic:Gate" pos="-1420,590,0">
   <Inputs SetClosed="0" AutoCloseCount="1" Reset="0"/>
  </Node>
  <Node Id="757" Class="Ark:Dialog:PlayTranscribeMessage" pos="2160,400,0">
   <Inputs dialogRule_Conversation="13680621263384740643" Queue="1" MinTimeSinceLastCall="0"/>
  </Node>
  <Node Id="758" Class="Time:Delay" pos="1420,410,0">
   <Inputs delay="90" resetOnInput="0"/>
  </Node>
  <Node Id="759" Class="Mission:GameTokenCheck" pos="930,410,0">
   <Inputs gametokenid_Token="361175835" CheckValue="true"/>
  </Node>
  <Node Id="2540" Class="Actor:LocalPlayer" pos="-2150,370,0">
   <Inputs/>
  </Node>
  <Node Id="2541" Class="Debug:DisplayMessage" pos="1660,540,0">
   <Inputs entityId="0" message="PlayerSomehowHasKeys" DisplayTime="3" posX="50" posY="100" fontSize="2" clr_Color="1,1,1" centered="0" ShowInLauncher="1"/>
  </Node>
  <Node Id="2543" Class="Ark:Objectives:ShowClue" pos="328.55524,822.70227,0">
   <Inputs objectiveclue_Clue="844024417328378473"/>
  </Node>
  <Node Id="2545" Class="Ark:Objectives:ShowClue" pos="-880,360,0">
   <Inputs objectiveclue_Clue="844024417328378001"/>
  </Node>
  <Node Id="2547" Class="Ark:Debug:ConsoleEvent" pos="-2890,970,0">
   <Inputs Command="givealexkey"/>
  </Node>
  <Node Id="2548" Class="Ark:Debug:ConsoleEvent" pos="-2910,1080,0">
   <Inputs Command="givemorgankey"/>
  </Node>
  <Node Id="2550" Class="Inventory:ItemAdd" pos="-2570,930,0">
   <Inputs entityId="0" archetype="ArkPickups.MissionItems.SelfDestructKey_Alex" quantity="1" playfanfare="0"/>
  </Node>
  <Node Id="2551" Class="Inventory:ItemAdd" pos="-2570,1080,0">
   <Inputs entityId="0" archetype="ArkPickups.MissionItems.SelfDestructKey_Morgan" quantity="1" playfanfare="0"/>
  </Node>
  <Node Id="2552" Name="Debug_add_keys" Class="_commentbox" pos="-2920,923,0">
   <Inputs TextSize="1" Color="0.27451,0.352941,0.705882" DisplayFilled="1" DisplayBox="1" SortPriority="16"/>
   <CommentBox Width="827" Height="293"/>
  </Node>
  <Node Id="2553" Class="Mission:GameTokenCheck" pos="1660,410,0">
   <Inputs gametokenid_Token="1008825921" CheckValue="true"/>
  </Node>
 </Nodes>
 <Edges>
  <Edge nodeIn="704" nodeOut="2" portIn="Trigger" portOut="Completed" enabled="1"/>
  <Edge nodeIn="705" nodeOut="2" portIn="Trigger" portOut="Completed" enabled="1"/>
  <Edge nodeIn="706" nodeOut="2" portIn="Trigger" portOut="Completed" enabled="1"/>
  <Edge nodeIn="7" nodeOut="3" portIn="In" portOut="Completed" enabled="1"/>
  <Edge nodeIn="7" nodeOut="9" portIn="In" portOut="Equal True" enabled="1"/>
  <Edge nodeIn="17" nodeOut="15" portIn="Trigger" portOut="Out" enabled="1"/>
  <Edge nodeIn="18" nodeOut="15" portIn="Add" portOut="Out" enabled="1"/>
  <Edge nodeIn="19" nodeOut="18" portIn="Trigger" portOut="Out" enabled="1"/>
  <Edge nodeIn="21" nodeOut="18" portIn="Activate" portOut="Out" enabled="1"/>
  <Edge nodeIn="2543" nodeOut="18" portIn="Show" portOut="Out" enabled="1"/>
  <Edge nodeIn="207" nodeOut="672" portIn="Activate" portOut="Added" enabled="1"/>
  <Edge nodeIn="635" nodeOut="672" portIn="Activate" portOut="Added" enabled="1"/>
  <Edge nodeIn="636" nodeOut="672" portIn="Trigger" portOut="Added" enabled="1"/>
  <Edge nodeIn="729" nodeOut="679" portIn="In" portOut="OnComplete" enabled="1"/>
  <Edge nodeIn="729" nodeOut="679" portIn="In" portOut="OnInterrupt" enabled="1"/>
  <Edge nodeIn="2" nodeOut="685" portIn="Complete" portOut="Active" enabled="1"/>
  <Edge nodeIn="685" nodeOut="693" portIn="Trigger" portOut="Out" enabled="1"/>
  <Edge nodeIn="687" nodeOut="693" portIn="Trigger" portOut="Out" enabled="1"/>
  <Edge nodeIn="681" nodeOut="729" portIn="Activate" portOut="Out" enabled="1"/>
  <Edge nodeIn="739" nodeOut="733" portIn="Show" portOut="True" enabled="1"/>
  <Edge nodeIn="740" nodeOut="733" portIn="Show" portOut="False" enabled="1"/>
  <Edge nodeIn="753" nodeOut="734" portIn="Show" portOut="True" enabled="1"/>
  <Edge nodeIn="754" nodeOut="734" portIn="Show" portOut="False" enabled="1"/>
  <Edge nodeIn="15" nodeOut="736" portIn="Complete" portOut="Out" enabled="1"/>
  <Edge nodeIn="759" nodeOut="736" portIn="Trigger" portOut="Out" enabled="1"/>
  <Edge nodeIn="734" nodeOut="738" portIn="check" portOut="Show" enabled="1"/>
  <Edge nodeIn="733" nodeOut="741" portIn="check" portOut="Show" enabled="1"/>
  <Edge nodeIn="756" nodeOut="749" portIn="In" portOut="onAdded" enabled="1"/>
  <Edge nodeIn="736" nodeOut="750" portIn="In" portOut="Out2" enabled="1"/>
  <Edge nodeIn="2545" nodeOut="750" portIn="Show" portOut="Out1" enabled="1"/>
  <Edge nodeIn="693" nodeOut="751" portIn="In" portOut="onAdded" enabled="1"/>
  <Edge nodeIn="755" nodeOut="751" portIn="In" portOut="onAdded" enabled="1"/>
  <Edge nodeIn="750" nodeOut="755" portIn="In" portOut="Out" enabled="1"/>
  <Edge nodeIn="688" nodeOut="756" portIn="Trigger" portOut="Out" enabled="1"/>
  <Edge nodeIn="750" nodeOut="756" portIn="In" portOut="Out" enabled="1"/>
  <Edge nodeIn="2541" nodeOut="758" portIn="Show" portOut="out" enabled="1"/>
  <Edge nodeIn="2553" nodeOut="758" portIn="Trigger" portOut="out" enabled="1"/>
  <Edge nodeIn="758" nodeOut="759" portIn="in" portOut="False" enabled="1"/>
  <Edge nodeIn="749" nodeOut="2540" portIn="entityId" portOut="entityId" enabled="1"/>
  <Edge nodeIn="751" nodeOut="2540" portIn="entityId" portOut="entityId" enabled="1"/>
  <Edge nodeIn="2550" nodeOut="2547" portIn="add" portOut="Triggered" enabled="1"/>
  <Edge nodeIn="2551" nodeOut="2548" portIn="add" portOut="Triggered" enabled="1"/>
  <Edge nodeIn="757" nodeOut="2553" portIn="Trigger" portOut="False" enabled="1"/>
 </Edges>
 <GraphTokens/>
</Graph>